database/__init__.py
database/__version__.py
database/database.py
database/encrypt.py
database/entry_points.py
villa_database_thanakijwanavit-0.0.6.dist-info/LICENSE
villa_database_thanakijwanavit-0.0.6.dist-info/METADATA
villa_database_thanakijwanavit-0.0.6.dist-info/WHEEL
villa_database_thanakijwanavit-0.0.6.dist-info/entry_points.txt
villa_database_thanakijwanavit-0.0.6.dist-info/top_level.txt
villa_database_thanakijwanavit-0.0.6.dist-info/RECORD
