Metadata-Version: 2.1
Name: villa-database-thanakijwanavit
Version: 0.0.6
Summary: save and load from database
Home-page: https://github.com/thanakijwanavit/villaWallet
Author: Nic Wanavit
Author-email: nwanavit@hatari.cc
License: Apache 2.0
Keywords: villa database
Platform: UNKNOWN
Classifier: Development Status :: 4 - Beta
Classifier: Intended Audience :: Developers
Classifier: Programming Language :: Python :: 3.8
Requires-Python: >=3.6.*
Requires-Dist: requests
Requires-Dist: boto3
